vedo/__init__.py
vedo/addons.py
vedo/applications.py
vedo/assembly.py
vedo/backends.py
vedo/cli.py
vedo/cmaps.py
vedo/colors.py
vedo/core.py
vedo/dolfin.py
vedo/file_io.py
vedo/grids.py
vedo/image.py
vedo/interactor_modes.py
vedo/mesh.py
vedo/plotter.py
vedo/pointcloud.py
vedo/pyplot.py
vedo/settings.py
vedo/shapes.py
vedo/transformations.py
vedo/utils.py
vedo/version.py
vedo/visual.py
vedo/volume.py
vedo/vtkclasses.py
vedo/examples/advanced/capping_mesh.py
vedo/examples/advanced/contours2mesh.py
vedo/examples/advanced/convex_hull.py
vedo/examples/advanced/cut_and_cap.py
vedo/examples/advanced/cut_with_mesh1.py
vedo/examples/advanced/cut_with_points1.py
vedo/examples/advanced/cut_with_points2.py
vedo/examples/advanced/diffuse_data.py
vedo/examples/advanced/fitline.py
vedo/examples/advanced/fitplanes.py
vedo/examples/advanced/fitspheres1.py
vedo/examples/advanced/fitspheres2.py
vedo/examples/advanced/geodesic_curve.py
vedo/examples/advanced/geological_model.py
vedo/examples/advanced/gyroid.py
vedo/examples/advanced/interpolate_field.py
vedo/examples/advanced/interpolate_scalar1.py
vedo/examples/advanced/interpolate_scalar2.py
vedo/examples/advanced/interpolate_scalar3.py
vedo/examples/advanced/interpolate_scalar4.py
vedo/examples/advanced/interpolate_scalar5.py
vedo/examples/advanced/line2mesh_quads.py
vedo/examples/advanced/line2mesh_tri.py
vedo/examples/advanced/measure_curvature.py
vedo/examples/advanced/mesh_smoother1.py
vedo/examples/advanced/mesh_smoother2.py
vedo/examples/advanced/meshquality.py
vedo/examples/advanced/moving_least_squares1D.py
vedo/examples/advanced/moving_least_squares2D.py
vedo/examples/advanced/multi_viewer2.py
vedo/examples/advanced/recosurface.py
vedo/examples/advanced/run_all.sh
vedo/examples/advanced/skeletonize.py
vedo/examples/advanced/spline_draw1.py
vedo/examples/advanced/spline_draw2.py
vedo/examples/advanced/splitmesh.py
vedo/examples/advanced/timer_callback0.py
vedo/examples/advanced/timer_callback1.py
vedo-2025.5.3.dist-info/FONT.LICENSE
vedo-2025.5.3.dist-info/LICENSE
vedo-2025.5.3.dist-info/METADATA
vedo-2025.5.3.dist-info/WHEEL
vedo-2025.5.3.dist-info/entry_points.txt
vedo-2025.5.3.dist-info/top_level.txt
vedo-2025.5.3.dist-info/RECORD
