Metadata-Version: 2.2
Name: vedo
Version: 2025.5.3
Summary: A python module for scientific visualization, analysis of 3D objects and point clouds.
Author-email: Marco Musy <marco.musy@embl.es>
Maintainer-email: Marco Musy <marco.musy@embl.es>
License: MIT License
Project-URL: Homepage, https://github.com/marcomusy/vedo
Project-URL: Documentation, https://vedo.embl.es
Project-URL: Repository, https://github.com/marcomusy/vedo
Project-URL: Changelog, https://github.com/marcomusy/vedo/blob/master/docs/changes.md
Keywords: vtk,numpy,3d,visualization,mesh,volume,point-cloud
Classifier: Intended Audience :: Science/Research
Classifier: Development Status :: 5 - Production/Stable
Classifier: License :: OSI Approved :: MIT License
Classifier: Programming Language :: Python :: 3
Classifier: Programming Language :: Python :: 3.7
Classifier: Programming Language :: Python :: 3.8
Classifier: Programming Language :: Python :: 3.9
Classifier: Programming Language :: Python :: 3.10
Classifier: Programming Language :: Python :: 3.11
Classifier: Topic :: Scientific/Engineering :: Visualization
Classifier: Topic :: Scientific/Engineering :: Physics
Classifier: Topic :: Scientific/Engineering :: Medical Science Apps.
Requires-Python: >=3.7
License-File: LICENSE
License-File: FONT.LICENSE
Requires-Dist: vtk
Requires-Dist: numpy
Requires-Dist: typing-extensions
Requires-Dist: Pygments
Provides-Extra: all
Requires-Dist: scipy; extra == "all"
